Metadata-Version: 2.4
Name: laiyuzheng-verification-code-gen
Version: 0.1.3
Summary: 基于FastMCP框架的验证码生成工具
Home-page: https://github.com/mcp-project/verification-code-generator
Author: MCP Developer
Author-email: MCP Developer <example@example.com>
Project-URL: Homepage, https://github.com/mcp-project/verification-code-generator
Project-URL: Bug Tracker, https://github.com/mcp-project/verification-code-generator/issues
Project-URL: Documentation, https://github.com/mcp-project/verification-code-generator/blob/main/README.md
Classifier: Programming Language :: Python :: 3
Classifier: License :: OSI Approved :: MIT License
Classifier: Operating System :: OS Independent
Classifier: Development Status :: 4 - Beta
Classifier: Intended Audience :: Developers
Classifier: Topic :: Software Development :: Libraries :: Python Modules
Classifier: Programming Language :: Python :: 3
Requires-Python: >=3.8
Requires-Dist: mcp[cli]>=1.13.0
Dynamic: author
Dynamic: home-page
Dynamic: requires-python
